circuits/d-flip-flop/dff.v
module dff (
    input  wire clk,
    input  wire rst_n,
    input  wire d,
    output reg  q
);

    // Ideal: no delay
    always @(posedge clk or negedge rst_n) begin
        if (!rst_n)
            q <= #1 1'b0;  // small delay for visibility
        else
            q <= #1 d;
    end

    // Timing checks (for simulation only)
    specify
        $setup(d, posedge clk, 1.0);   // t_su = 1 ns
        $hold(posedge clk, d, 0.5);    // t_h = 0.5 ns
    endspecify

endmodule

circuits/d-flip-flop/dff_tb.v
// dff_tb.v
`timescale 1ns / 1ps

module dff_tb;

    reg clk;
    reg rst_n;
    reg d;
    wire q;

    // Instantiate DFF
    dff uut (
        .clk(clk),
        .rst_n(rst_n),
        .d(d),
        .q(q)
    );


    // Clock generator (10 ns period = 100 MHz)
    always begin
        #5 clk = ~clk;  // 5 ns half-period
    end

    initial begin
        // Initialize
        clk = 0;
        rst_n = 0;
        d = 0;

        // Release reset
        #15 rst_n = 1;

        // ---- 1. Correct operation ----
        #10 d = 1;          // Change D at t=25 ns
        #20 d = 0;          // Next change at t=45 ns (well before clk@50ns)

        // ---- 2. Setup time violation ----
        // Clock edges at: 10, 20, 30, 40, 50, 60, 70, ...
        // Next clock at t=70 ns → D must be stable by t=69 ns (t_su=1ns)
        #15 d = 1;          // Change D at t=60 ns → OK
        #8.5 d = 0;         // Change D at t=68.5 ns → VIOLATION! (only 1.5 ns before clk)
        #1.0 d = 1;         // Change at t=69.5 ns → even worse (0.5 ns before clk)

        // ---- 3. Hold time violation ----
        // After clk@70ns, D must stay stable until t=70.5 ns
        #0.3 d = 0;         // Change at t=69.8 ns → still before clk → OK
        // Now wait for clk@80ns
        #10.2;              // Advance to t=80.0 ns (clk posedge)
        #0.3 d = 1;         // Change at t=80.3 ns → VIOLATION! (only 0.3 ns after)

        // Finish
        #20 $finish;
    end

    // Optional: dump waveforms
    initial begin
        $dumpfile("dff.vcd");
        $dumpvars(0, dff_tb);
    end

endmodule

circuits/d-flip-flop/dff.vcd
$date
	Wed May 13 12:16:14 2026
$end
$version
	Icarus Verilog
$end
$timescale
	1ps
$end
$scope module dff_tb $end
$var wire 1 ! q $end
$var reg 1 " clk $end
$var reg 1 # d $end
$var reg 1 $ rst_n $end
$scope module uut $end
$var wire 1 " clk $end
$var wire 1 # d $end
$var wire 1 $ rst_n $end
$var reg 1 ! q $end
$upscope $end
$upscope $end
$enddefinitions $end
$comment Show the parameter values. $end
$dumpall
$end
#0
$dumpvars
0$
0#
0"
0!
$end
#5000
1"
#10000
0"
#15000
1"
1$
#20000
0"
#25000
1!
1"
1#
#30000
0"
#35000
1"
#40000
0"
#45000
0!
1"
0#
#50000
0"
#55000
1"
#60000
0"
1#
#65000
1!
1"
#68500
0#
#69500
1#
#69800
0#
#70000
0"
#75000
0!
1"
#80000
0"
#80300
1#
#85000
1!
1"
